viewclust_vis/__init__.py
viewclust_vis/_version.py
viewclust_vis/cumu_plot.py
viewclust_vis/delta_plot.py
viewclust_vis/insta_plot.py
viewclust_vis/job_scatter.py
viewclust_vis/job_stack.py
viewclust_vis/show_job_use.py
viewclust_vis/summary_page.py
viewclust_vis/use_suite.py
viewclust_vis/viewclust_vis.py
viewclust_vis/viol_plot.py
viewclust_vis-0.4.0.dist-info/AUTHORS.rst
viewclust_vis-0.4.0.dist-info/LICENSE
viewclust_vis-0.4.0.dist-info/METADATA
viewclust_vis-0.4.0.dist-info/WHEEL
viewclust_vis-0.4.0.dist-info/top_level.txt
viewclust_vis-0.4.0.dist-info/RECORD
