Metadata-Version: 2.1
Name: viewclust-vis
Version: 0.4.0
Summary: Extension to ViewClust containing dashboard submodules and more.
Home-page: https://github.com/Andesha/viewclust_vis
Author: Tyler Collins
Author-email: tk11br@sharcnet.ca
License: MIT license
Keywords: viewclust_vis
Platform: UNKNOWN
Classifier: Development Status :: 2 - Pre-Alpha
Classifier: Intended Audience :: Developers
Classifier: License :: OSI Approved :: MIT License
Classifier: Natural Language :: English
Classifier: Programming Language :: Python :: 3
Classifier: Programming Language :: Python :: 3.7
Classifier: Programming Language :: Python :: 3.8
Requires-Python: >=3.5
License-File: LICENSE
License-File: AUTHORS.rst
Requires-Dist: numpy
Requires-Dist: pandas
Requires-Dist: plotly
Requires-Dist: viewclust
